{"parent":null,"pid":15416,"argv":["C:\\Program Files\\nodejs\\node.exe","C:\\Users\\I538959\\Documents\\kinosystem\\kino-backend\\node_modules\\mocha\\bin\\mocha","-r","ts-node/register","./src/test/*.test.ts","--exit"],"execArgv":[],"cwd":"C:\\Users\\I538959\\Documents\\kinosystem\\kino-backend","time":1631283822449,"ppid":15944,"coverageFilename":"C:\\Users\\I538959\\Documents\\kinosystem\\kino-backend\\nyc_output\\56e9943c-58e3-449a-bd86-d638ec85a1a6.json","externalId":"","uuid":"56e9943c-58e3-449a-bd86-d638ec85a1a6","files":["C:\\Users\\I538959\\Documents\\kinosystem\\kino-backend\\src\\app.ts","C:\\Users\\I538959\\Documents\\kinosystem\\kino-backend\\src\\api\\routes\\routes.ts","C:\\Users\\I538959\\Documents\\kinosystem\\kino-backend\\src\\api\\routes\\authentication\\authentication.router.ts","C:\\Users\\I538959\\Documents\\kinosystem\\kino-backend\\src\\api\\routes\\authentication\\authentication.controller.ts","C:\\Users\\I538959\\Documents\\kinosystem\\kino-backend\\src\\api\\models\\user.model.ts","C:\\Users\\I538959\\Documents\\kinosystem\\kino-backend\\src\\api\\utils\\utils.ts","C:\\Users\\I538959\\Documents\\kinosystem\\kino-backend\\src\\api\\routes\\user\\user.router.ts","C:\\Users\\I538959\\Documents\\kinosystem\\kino-backend\\src\\api\\routes\\user\\user.controller.ts","C:\\Users\\I538959\\Documents\\kinosystem\\kino-backend\\src\\api\\middlewares\\auth.middlewares.ts","C:\\Users\\I538959\\Documents\\kinosystem\\kino-backend\\src\\api\\routes\\hall\\hall.router.ts","C:\\Users\\I538959\\Documents\\kinosystem\\kino-backend\\src\\api\\routes\\hall\\hall.controller.ts","C:\\Users\\I538959\\Documents\\kinosystem\\kino-backend\\src\\api\\models\\hall.model.ts","C:\\Users\\I538959\\Documents\\kinosystem\\kino-backend\\src\\api\\routes\\customer\\customer.router.ts","C:\\Users\\I538959\\Documents\\kinosystem\\kino-backend\\src\\api\\routes\\customer\\customer.controller.ts"]}